example.py
wocecolormap.py
wocecolor-0.0.1.dist-info/LICENSE
wocecolor-0.0.1.dist-info/METADATA
wocecolor-0.0.1.dist-info/WHEEL
wocecolor-0.0.1.dist-info/top_level.txt
wocecolor-0.0.1.dist-info/RECORD
